sqlalchemy_monetdb/__init__.py
sqlalchemy_monetdb/base.py
sqlalchemy_monetdb/compiler.py
sqlalchemy_monetdb/dialect.py
sqlalchemy_monetdb/monetdb_types.py
sqlalchemy_monetdb/provision.py
sqlalchemy_monetdb/requirements.py
test/__init__.py
test/conftest.py
test/test_doc.py
test/test_suite.py
sqlalchemy_monetdb-2.0.0.dist-info/LICENSE
sqlalchemy_monetdb-2.0.0.dist-info/METADATA
sqlalchemy_monetdb-2.0.0.dist-info/WHEEL
sqlalchemy_monetdb-2.0.0.dist-info/entry_points.txt
sqlalchemy_monetdb-2.0.0.dist-info/top_level.txt
sqlalchemy_monetdb-2.0.0.dist-info/RECORD
