Metadata-Version: 2.1
Name: sqlalchemy-monetdb
Version: 2.0.0
Summary: SQLAlchemy dialect for MonetDB
Home-page: https://github.com/MonetDB/sqlalchemy-monetdb
Author: Gijs Molenaar
Author-email: gijsmolenaar@gmail.com
License: MIT
Keywords: MonetDB,SQLALchemy
Platform: UNKNOWN
Classifier: Topic :: Database
Classifier: Topic :: Database :: Front-Ends
Classifier: Topic :: Database :: Database Engines/Servers
Classifier: Development Status :: 5 - Production/Stable
Classifier: Environment :: Console
Classifier: Intended Audience :: Developers
Classifier: Programming Language :: Python :: 3.8
Classifier: Programming Language :: Python :: 3.9
Classifier: Programming Language :: Python :: 3.10
Classifier: Programming Language :: Python :: 3.11
Classifier: Programming Language :: Python :: Implementation :: CPython
Classifier: Programming Language :: Python :: Implementation :: PyPy
Requires-Python: >=3.8
License-File: LICENSE
Requires-Dist: pymonetdb (>=1.8.2)
Requires-Dist: sqlalchemy (>=2.0.34)
Provides-Extra: test
Requires-Dist: coverage (>=7.3.0) ; extra == 'test'
Requires-Dist: flake8 (>=6.1.0) ; extra == 'test'
Requires-Dist: mypy (>=1.5.1) ; extra == 'test'
Requires-Dist: pytest-cov (>=4.1.0) ; extra == 'test'
Requires-Dist: pytest (>=7.4.0) ; extra == 'test'
